free_proxy_list_client/__init__.py
free_proxy_list_client/client.py
free_proxy_list_client-2024.5.19.0.dist-info/LICENSE
free_proxy_list_client-2024.5.19.0.dist-info/METADATA
free_proxy_list_client-2024.5.19.0.dist-info/WHEEL
free_proxy_list_client-2024.5.19.0.dist-info/top_level.txt
free_proxy_list_client-2024.5.19.0.dist-info/zip-safe
free_proxy_list_client-2024.5.19.0.dist-info/RECORD
