Metadata-Version: 2.1
Name: free-proxy-list-client
Version: 2024.5.19.0
Summary: Simple python client to https://free-proxy-list.net/
Home-page: UNKNOWN
Author: Sergei Belousov aka BeS
Author-email: sergei.o.belousov@gmail.com
License: UNKNOWN
Platform: UNKNOWN
Classifier: Programming Language :: Python :: 3
License-File: LICENSE
Requires-Dist: beautifulsoup4
Requires-Dist: requests
